{"hash":"70fad8ab08ff46a8e846ad4309230ad739a7d952","data":{"allNew":{"pageInfo":{"totalPages":10,"currentPage":2},"edges":[{"node":{"id":"F0Ed3754-23C1-e0Fb-Ac55-A8fFc9cc2fa2","title":"除准太命名","banner":"http://dummyimage.com/200x100/79f2ad","date":"2016-12-05","summary":"矿根提转先感看运地受众美东眼离对。"}},{"node":{"id":"3E76eEE9-b78F-7eCd-8cA5-67fEDfF8fbf8","title":"党太这来例林民","banner":"http://dummyimage.com/200x100/f2e579","date":"2016-11-28","summary":"难便照其划取军把那划步八他须级。"}},{"node":{"id":"9cf8f1EA-bECD-DbcA-F427-4dDbec1C5cA8","title":"线办命是特","banner":"http://dummyimage.com/200x100/9ef279","date":"2016-10-16","summary":"持心关同周整满放六四队支。"}},{"node":{"id":"CfFff4b1-f2dE-Fc7B-A4Fb-3c2Ac6C1FB3e","title":"确子少心容段","banner":"http://dummyimage.com/200x100/79f2d6","date":"2016-06-08","summary":"听低无走转性活一体最复第南值离精。"}},{"node":{"id":"CecE61E2-061f-2C5d-917d-56EcFb32d13f","title":"四看代六成采","banner":"http://dummyimage.com/200x100/79f2bd","date":"2015-11-22","summary":"意江值土离其了空开风把命品。"}},{"node":{"id":"1DCfcD61-cF5D-9587-6F23-2dfC3A4ddeb4","title":"半制委走指运在","banner":"http://dummyimage.com/200x100/a879f2","date":"2014-05-27","summary":"月提比农质运安更断组意消议。"}},{"node":{"id":"32d3807b-fD35-b471-e8f0-7473DD9F927F","title":"劳连法除","banner":"http://dummyimage.com/200x100/9f79f2","date":"2014-05-20","summary":"达格论出入象周水步必样程近使。"}},{"node":{"id":"54bbE06B-c5E9-A9b5-e782-3cf777DAbdE8","title":"更受历中商","banner":"http://dummyimage.com/200x100/cdf279","date":"2013-05-29","summary":"后立运性变行小图实它区人变水接是于。"}},{"node":{"id":"3d1E3C1f-1ECc-81ED-ecB5-b233dCDeEC51","title":"便入长利压","banner":"http://dummyimage.com/200x100/a8f279","date":"2012-07-24","summary":"斯江难素同示府美计样群研火问。"}},{"node":{"id":"99C45f74-DAdd-3edF-a35d-89B589Df798f","title":"格用成布求线","banner":"http://dummyimage.com/200x100/79ccf2","date":"2012-03-11","summary":"组广市作除则片今商先立口基转展别其。"}}]}},"context":{}}