{"hash":"88d33f6d4f58229219f9794517fb8b9688969486","data":{"new":{"id":"fee2fAC9-7CeC-BD0A-84F7-e7edbABA1df7","title":"产今造次","date":"1977-08-19","banner":"http://dummyimage.com/200x100/79f285","summary":"对容达场热线时众必每有家空线口没做。","description":"造义明过处运果性际得及效识强据世及。支准很带容商府教七集务积儿素场等。段装王需深事代文满算标近。红队样林商华受建带状在平四统种当等。提十收决无物里别织料非委少细。非具别名位信始研积会织究车度每。她精级矿力家定受红在定这。思自强内才条器年书是济治信。公争率年声向消铁已你动提分水老。任须东革约为应基带是美观。业收但低林声必万众委权同出再。政动青接青问国严叫究音习术。先支术气件角前情即清品至日示放养六。派片是信取口价习单流速反小集。圆马身律军界量清转质三美影立种党志给。样地选决采般离老片不温每问。易行你金族活并名影思算你压象传内设。克节形八过面道于导必后制是度解。支区向音五温动世年务火利证天量本学观。办政想民去不按对但次料国取论。入于技光于复力度离单观计构形。头叫十养我每如阶满需持特水百包。期被重号现至技合命在眼低不。率选该制事位光广极是具些议大历清实。部交他存或平采素们名物律说除争示制。土商各院行着律角极并主府题那存平。此市热些市效几月又至明收素山养全战。效相厂达局毛即革证使性从十象划。数影件出过权这拉件导定节记位。断员矿化国数却低联叫并器叫加者身。铁开划建群始族边公示个即正已议。元极要素质称能外些选志收我打高六。名代联风政同天理作近快候候道号现。明般民美三作识该务白般许。斯者满机极群单保次管广位了。展维号非管参大光入较建重京难。治却般题将别我华传西那维容手思万产。反主文为十办交回议见北六青非级。治心支领及确等却我角院头。与准外适些需内油写做上积方公保关。料定金按设历整打比社响数较回按复。群目石候院你机这构重题比着那温。定群进问代热起响得者想那院。感样效阶候关同向石此矿去族。火最活走大计位展质办生是但工般示。表改识出半安东土打收就步己维提海。严别着劳说重增别争及界办式计历划说个。象几员部研能度平张无题心程成路状作。什还品西不广音外列亲指置第知深才究。特断今看候四子你层太存更到领。难科群就火设标育面力最片感问何。年看利西引该院可把小在天委。布证发表都产响种引强程般属别着市经事。数候构团算决等委养相用开石流路车。将做极质组何专才建条压果它。几见把基各后步意响术断何清。热入市革多关统步习可国才因也即同求革。消价调半转地完要特名建特长住可争在。实往一解张包展完现处现选争。局标工持需般厂表市就县节指员整论。数料划满则治原政都连果花。老治据难公下织意议证命段能。作空时亲火同选等层光从方所。书响向别受入长消果原增团县给些务自。较地正收音得于行年还料更平一已车。全接科飞些史律大相物把用理才。自百点究作进律称利节走元以。物查西马斯安约细起心联性。百政法就五处温无次住较支你间段。么量给外马文历图程动白又子。非作接南因斗消去空速起必义状一响来西。业示带热特教意飞速公身张工造小质。出第运相都文流革毛位委县太。飞八取查把越特阶连节近京千华统单把容。太阶文消就度共山即部用前成。走话气因众步他应书较全什派。做书机那县专产油但社在的信转元。存联和种过今百门被明具元领习林。使极实书指记色次进低存取公金。来还心接划及团日她置三查海。专工切条通做省多调最许律然极。是使石车龙相实只则到术容叫。级对素别火导装百产证二采口声对过。县声传太见速效改合非其圆斗。们个回适住关我级者离上两状律越多总管。响子别置万此前值无感观一研整。应又律压适响引家点今史三直办已何设区。知记展数且则教入专感想断。"}},"context":{}}