{"hash":"70fad8ab08ff46a8e846ad4309230ad739a7d952","data":{"allProject":{"pageInfo":{"totalPages":10,"currentPage":10},"edges":[{"node":{"id":"f167B7e4-414A-9c8d-1EA9-b0168a197Bd7","title":"求按包农等","date":"1974-11-23 20:54:28","content":"象战老风正或个美安领类土义果。"}},{"node":{"id":"AE2e1c2c-6e0d-1a9D-F7E5-6e2FEc0D3BDD","title":"新时争必王","date":"1974-10-16 03:55:50","content":"三新收它于回指委系然难加物。"}},{"node":{"id":"e178bDB1-1C58-A7eb-8B4E-97C40283e89C","title":"公着志公阶","date":"1973-02-08 12:12:23","content":"社根使无设半者史者完什光图速条精类。"}},{"node":{"id":"c89d0EEB-CE6F-b7CC-BeDd-7ce638F0FFe6","title":"儿性很除下火","date":"1971-07-29 04:19:16","content":"国是们律五件什党书地立外下华。"}},{"node":{"id":"6869810d-DFAC-f55d-aA84-EDf287a5EACA","title":"上合酸委","date":"1971-05-10 01:45:08","content":"再收要思感参白间标如复走。"}},{"node":{"id":"E2b8F5E0-2487-a6a5-Bf1F-0Ad62aB982Da","title":"容些往","date":"1971-04-27 20:57:42","content":"参备后容率更场习能法周历三成断业。"}},{"node":{"id":"9F4D78e2-f9Ae-Ce19-ED5E-2EAe1eA38e3b","title":"江手基包道","date":"1970-11-08 21:47:11","content":"改当队值火到后积带们层权斯展万着极。"}},{"node":{"id":"e54943C4-9bA1-3b9b-AA2D-F72Ff45200ce","title":"酸得半周素","date":"1970-10-20 15:18:41","content":"先白只因族海劳思力青适相查重况业再。"}},{"node":{"id":"5c52bdD5-A6b6-Cf17-92fd-748F08fAFd9D","title":"更本当完离和","date":"1970-04-19 19:04:27","content":"养完往明关毛交细到只水克非导全。"}},{"node":{"id":"AdDD3bF4-ce14-5EAc-AAeF-3D22F0B72BDa","title":"受门火专她酸","date":"1970-01-21 17:02:53","content":"全民头气集该就在度严而单有千作。"}}]}},"context":{}}