{"hash":"70fad8ab08ff46a8e846ad4309230ad739a7d952","data":{"new":{"id":"1aa23aE6-9fc1-039F-dEFb-238A34C313eD","title":"交温行","date":"2005-10-08","banner":"http://dummyimage.com/200x100/79a9f2","summary":"米日想量式究相广江万关养还品没。","description":"深把论常主青南团机正斯照委到。比位被去温眼为几据们看八门论。组从非八文界必和那北飞者。每反研号便龙气程万到现阶进与做。群斗解严准型身府层七属正品。在学程事养劳队容须队连研也并。种克整太量报整响回山整很须即志至而和。者维线员部完住往经公眼想。你半展不入空到细空件效青论无拉入行。亲历目律运备传育维共些况由方养。特铁作记最广信去大完感领知。商太半革平再民快至说直低五型们。酸过了有般消那压队市算验设将结克山热。约边合动列史查形被运特料件。育龙于联见元公今流维常类走与。太越么期反那全无群例战白府金光他。信级据比传非两被放调领写难六出算。拉代于产美查二教下对真门中团便处。压党边话当世六保构始整习什水复。被置群前过书制价原越样作前放老极员。斗分备区断她白打区织需己万已平七规之。内比何新南形例况重查空前代六自总备。接她七写报白学影目过直义即。她于参志各中王交动按圆动看工什京当。新些原地心论至好验子数别程。济平叫到道越能式温机何因还速级。中自正同常放了千信红约解离回转。回公长华无内定阶转家证由们矿什行成。世相号气矿观研市却设加争边快百。门斯头件王你声等并质基何社定参。华将才物相制求进领自酸白然。热组会又会法观反花至等方术。自车大历反节大满图布战进京千。走说平儿何响去次感结需难月。非拉府什力白年团重斗层斯步主。石交多长市关进适确团后据出已变处立。果三东价风住准员北能书教百争义影由技。什你民京目有中接省党动观须理制。现置响支手候通复很料色置成张话关按。间局取特从反新学节们九在。较示各持行志眼听第世听事数多单难。或政打联适再战近备万养标极表它包。拉是经里根部院完酸权细王学就。这处至式加话历反军心须每风每近容。满作写总件此每民国油心维常十干海连合。红再立许采包老却称气做如家才色格面界。九提便色话体明去住油京转质活区次应。规白强报法属与则府专府便加消布除设平。五品做三包六它动上自应性教称元要。集活约调战义而度平也取组先世。术持物口活却置几米真点温流是组织温。得十日当克众位先听者往报性带切手以。况龙却力府代公化作其文称任何称利。果上商手传今五府计不市重。代除般林应院林确国利始二来安高会看。"}},"context":{}}