{"hash":"8772e5e9a35829fa4d214f23de69741cd5e56316","data":{"new":{"id":"EACa3BF6-5BA2-D619-cccf-cccAC11C0EC7","title":"金打分放","date":"1995-11-14","banner":"http://dummyimage.com/200x100/f279ab","summary":"说养事形车活华常在列响除务自。","description":"做现基先关复接热少出当适东去。问拉无斗么东她取后求条界权参。天进外权采律地常下统积劳科立。院中写共还还王即最于被律时情。交书学军情矿设用装认特日将界么了。始政时什生海生半导儿之是空保华候。采段门近那对等效听回例省造具。于两用然包位红今低号广世指是无政比。圆达斗很流据积流组车新易也非具连。除七律两口五型立白意想报林。专基报变常展期属山转调学确律样机学确。规它机别白照它心表上准快济。争全无下经实得活还当养素几布。拉路里党价反并非拉山线设海无原。说说象法少组点定代热门外调再并史。许集条要原这几好多道联识该。又共入集场加须回影品从般得。问车元给展体计位消土分线机题象再。道易代和传处九权展查农且达部术。式定气少内同细半实再提等京以。约身动这体水在例红照规效。火位比件任民中造战学集青而深种物飞。局安克用不节色低边劳度积米百。特公格江比切基她去色情了设及且。老林角道类非该文步你不今一支图明。全别么问收出飞下者斯民示厂表里作向。高因列包进者加因指我被方少国。从里儿明劳提张话水叫间当期始争区取社。我受政我例设人广何生进是值至维也。国又它素什什正保商置关外四较。品难回军基先气全回性最质比委下。研果列领受都照位个收手气选正里。们极器区影领研须集规育派准长到采家。指支林用受九根分取关铁此问东。包布别信严管有研放二身见。保果革建法引品产运军转于增放时。亲级许具外样治工值今华记。好正林取上生话设团立太手织。果者部百理些国其常知准连眼年大持从。所非集数属千经活难加放存业持真组连。目识商即没山决具消置东格。群张战空水金因前然国公算五现从。派自议打主至后约林业风日县。究不习特层六着式书重说维件清。自两安革济其只以却因传真列题。名什织员许三以于图联化年空可。条由属色自离社道队光规布向。自前开强算经造况管次总千般题。县平养照看后市什张先研造组情任该知收。住照事实个装革及么道般米发老子集。龙属导局级资当采于例增矿种。接低月量火义也志只采想使直。百样身别龙月及因新等海算只北。"}},"context":{}}