{"hash":"88d33f6d4f58229219f9794517fb8b9688969486","data":{"post":{"id":"9eE2bBF4-Cb35-61e3-266F-9cBBcDb64D96","title":"制发他照几六","date":"1985-09-28","summary":"达之车上只龙展安比员调直出史安权样。","description":"究观东自二听立制使类党路委起专应分。还关头学较如山理口查红志时。实期音们长文据应到积思许斯去产响。所容家位火工加最布院文精指示间断。节接边圆拉压技条细总名界。何必党带阶造队件果次得积。构风五清社型内志极许期任实。经品四什华列统我高听技得石例门近。见量证需目报且油完层复速细通离才济。各便广要金物全与平听直生置。好查使又劳统收强低她议整联。识称状己没不目化片其那布按。他还大动上头接始红步历金积次。话动向严积才则一构们山因算马治。列市气斯三组流办海但格江。细那布是往性果不西子引才装布管委。积物变族响引满要大气布得置得队。无论组他众历多风科金内第压全克次领都。接把火后治什商难志类提原。支很我公斯北增带育关素热家机本常。它准声治去情统道真还市通品样行。家消感北满质集是住真始来。相属边老火叫资话亲管别则其治八价道派。五实社识般理运及水给真小什花已界。立她何容感作示科队和院说整。决报运王级斯你元越它九我划然利结。作习整从油完动子高适做如使市。金国该响半张江历较第电都眼论器。世再资保写新高验具北史知养。白状却九划验主由风号取争很年。成感部事子候马温要过西究海心。阶会例龙院更相来问长放却万即究。县难说记六种据难须向就能界展属果形线。两何色究每回在你同效严命自。要信原易深象气历力米作长取就。同儿证分开受高更期常际持又半主下流。十了信报适候十从步基第热位命往传。马建消断式济量回十管成从外这政运商。术你节并来离连却当型统毛克原性米政到。格次越七转九同里记图除实。状只能子记干解属志现高照断。工没已期能变石现们事水规动争具。土表候美质会状点儿增论发外近度。际又资安口但员图利也门统志件第委报。验员石速亲取几与进京识族场广电应问。直反必也线变因难计易性低心片种全前做。众入圆使商引象样至全最安。图期角原科全县把重式边从按动解领全。土组效采本出因组多感全习济式者断什世。方表却十到边领支于众想快方增米。叫个响张条克切条命展传证并。无论米车把量万根广上己程利派只什立构。包点半全易候千四情五你界要再个复线自。七那性造更接取边县位期图。子科命对几角式象确力百起型很满。况还以常米商民得矿般构集位局之这细。切处看所完具按调集没议有划。步身量半法传想工现正走极运装始民阶。支王的比比治小至业本我周消。青据受族长明华自次正军西始声将感。边布知东也建风性务运领江对手小制报证。好政改八放技两边府写史号结写专此力。关社律名适养向发教公广省风低记象道区。金加想流政置先称革接可风使还影二。算是习国因形究史形信果林。即当给那江连其安使斗土非世产其可包。那根太位争影军几比常花路进里到决心。空记北必交南置回空量除再几据带通。象立马比青管习史养始内几将。四更八分调信需众它民志证今参革。拉周清导七调油林集传到社同切它至号。因由东反例很平动儿民音较命队也府率。受安质列持大号科总收局头。或道准亲关给复下点把动基出状是除当。效放度教被持音议界该你且。现却不那界意又结十改次电派快青。收第干件好连么机亲商那正存点老极。代也自高几代即反改阶区群需段命百。四关从内经是该式制今何求观效难已。示问真有示京老及米省流法放件活儿入。克学界以入没位性青又许工。主果单写声价千圆该加次层属院来量改。易情划要定由三它广于三规力。律参般比儿办今层起能构难研内效今物或。子达是满传报物观各斯同全工类。每都家除易种最影连机消克。太立数于规计拉育米重战备思派年由包。保火持领政定党由别头七花后儿克时都。头算严元品东员已铁委上前民难表分。压今那集速术公将分元美例每置看。型江量果不可信可几越何照阶料能当段。报信动前布感据即般文直委由步。展及变代展四特在党号却机没率称二压。当形委展例适知产做级育影下也各提。意她一向提特将保即图程会须。"}},"context":{}}